utool/DynamicStruct.py
utool/Preferences.py
utool/Printable.py
utool/__init__.py
utool/__main__.py
utool/_version.py
utool/oldalg.py
utool/sandbox.py
utool/util_alg.py
utool/util_aliases.py
utool/util_arg.py
utool/util_assert.py
utool/util_autogen.py
utool/util_cache.py
utool/util_class.py
utool/util_config.py
utool/util_const.py
utool/util_cplat.py
utool/util_csv.py
utool/util_dbg.py
utool/util_decor.py
utool/util_depricated.py
utool/util_dev.py
utool/util_dict.py
utool/util_func.py
utool/util_git.py
utool/util_grabdata.py
utool/util_graph.py
utool/util_gridsearch.py
utool/util_hash.py
utool/util_import.py
utool/util_inject.py
utool/util_inspect.py
utool/util_io.py
utool/util_ipynb.py
utool/util_iter.py
utool/util_latex.py
utool/util_list.py
utool/util_logging.py
utool/util_num.py
utool/util_numpy.py
utool/util_parallel.py
utool/util_path.py
utool/util_print.py
utool/util_profile.py
utool/util_progress.py
utool/util_project.py
utool/util_regex.py
utool/util_resources.py
utool/util_set.py
utool/util_setup.py
utool/util_six.py
utool/util_sqlite.py
utool/util_str.py
utool/util_sysreq.py
utool/util_tags.py
utool/util_tests.py
utool/util_time.py
utool/util_type.py
utool/util_ubuntu.py
utool/util_web.py
utool/util_win32.py
utool/_internal/__init__.py
utool/_internal/meta_util_arg.py
utool/_internal/meta_util_cache.py
utool/_internal/meta_util_constants.py
utool/_internal/meta_util_cplat.py
utool/_internal/meta_util_dbg.py
utool/_internal/meta_util_git.py
utool/_internal/meta_util_iter.py
utool/_internal/meta_util_path.py
utool/_internal/meta_util_six.py
utool/_internal/py2_syntax_funcs.py
utool/_internal/randomwrap.py
utool/_internal/util_importer.py
utool/_internal/win32_send_keys.py
utool/experimental/__init__.py
utool/experimental/bytecode_optimizations.py
utool/experimental/dynamic_connectivity.py
utool/experimental/euler_tour_tree_avl.py
utool/experimental/pandas_highlight.py
utool/tests/__init__.py
utool/tests/_oldtest_decor.py
utool/tests/_oldtest_hash.py
wbia_utool-4.0.5.dist-info/LICENSE
wbia_utool-4.0.5.dist-info/METADATA
wbia_utool-4.0.5.dist-info/WHEEL
wbia_utool-4.0.5.dist-info/top_level.txt
wbia_utool-4.0.5.dist-info/RECORD
