Metadata-Version: 2.1
Name: wbia-utool
Version: 4.0.5
Summary: utool - Useful utilities and the kitchen sink
Home-page: https://github.com/WildbookOrg/wbia-utool
Author: Jon Crall, Jason Parham, WildMe Developers
Author-email: dev@wildme.org
License: BSD
Classifier: Development Status :: 6 - Mature
Classifier: License :: OSI Approved :: BSD License
Classifier: Intended Audience :: Developers
Classifier: Intended Audience :: Science/Research
Classifier: Operating System :: MacOS :: MacOS X
Classifier: Operating System :: Unix
Classifier: Topic :: Software Development :: Libraries :: Python Modules
Classifier: Topic :: Utilities
Classifier: Programming Language :: Python :: 3
Classifier: Programming Language :: Python :: 3.5
Classifier: Programming Language :: Python :: 3.6
Classifier: Programming Language :: Python :: 3.7
Classifier: Programming Language :: Python :: 3.8
License-File: LICENSE
Requires-Dist: delorean
Requires-Dist: gitpython
Requires-Dist: lockfile
Requires-Dist: networkx
Requires-Dist: numpy
Requires-Dist: opencv-contrib-python-headless
Requires-Dist: ordered-set
Requires-Dist: pandas
Requires-Dist: parse
Requires-Dist: pint
Requires-Dist: psutil
Requires-Dist: pyparsing
Requires-Dist: requests
Requires-Dist: six
Requires-Dist: ubelt
Provides-Extra: all
Requires-Dist: cmake ; extra == 'all'
Requires-Dist: ninja ; extra == 'all'
Requires-Dist: scikit-build ; extra == 'all'
Requires-Dist: setuptools ; extra == 'all'
Requires-Dist: setuptools-scm[toml] ; extra == 'all'
Requires-Dist: wheel ; extra == 'all'
Requires-Dist: delorean ; extra == 'all'
Requires-Dist: gitpython ; extra == 'all'
Requires-Dist: lockfile ; extra == 'all'
Requires-Dist: networkx ; extra == 'all'
Requires-Dist: numpy ; extra == 'all'
Requires-Dist: opencv-contrib-python-headless ; extra == 'all'
Requires-Dist: ordered-set ; extra == 'all'
Requires-Dist: pandas ; extra == 'all'
Requires-Dist: parse ; extra == 'all'
Requires-Dist: pint ; extra == 'all'
Requires-Dist: psutil ; extra == 'all'
Requires-Dist: pyparsing ; extra == 'all'
Requires-Dist: requests ; extra == 'all'
Requires-Dist: six ; extra == 'all'
Requires-Dist: ubelt ; extra == 'all'
Requires-Dist: brunette ; extra == 'all'
Requires-Dist: codecov ; extra == 'all'
Requires-Dist: coverage ; extra == 'all'
Requires-Dist: pytest ; extra == 'all'
Requires-Dist: pytest-cov ; extra == 'all'
Requires-Dist: xdoctest ; extra == 'all'
Provides-Extra: build
Requires-Dist: cmake ; extra == 'build'
Requires-Dist: ninja ; extra == 'build'
Requires-Dist: scikit-build ; extra == 'build'
Requires-Dist: setuptools ; extra == 'build'
Requires-Dist: setuptools-scm[toml] ; extra == 'build'
Requires-Dist: wheel ; extra == 'build'
Provides-Extra: runtime
Requires-Dist: delorean ; extra == 'runtime'
Requires-Dist: gitpython ; extra == 'runtime'
Requires-Dist: lockfile ; extra == 'runtime'
Requires-Dist: networkx ; extra == 'runtime'
Requires-Dist: numpy ; extra == 'runtime'
Requires-Dist: opencv-contrib-python-headless ; extra == 'runtime'
Requires-Dist: ordered-set ; extra == 'runtime'
Requires-Dist: pandas ; extra == 'runtime'
Requires-Dist: parse ; extra == 'runtime'
Requires-Dist: pint ; extra == 'runtime'
Requires-Dist: psutil ; extra == 'runtime'
Requires-Dist: pyparsing ; extra == 'runtime'
Requires-Dist: requests ; extra == 'runtime'
Requires-Dist: six ; extra == 'runtime'
Requires-Dist: ubelt ; extra == 'runtime'
Provides-Extra: tests
Requires-Dist: brunette ; extra == 'tests'
Requires-Dist: codecov ; extra == 'tests'
Requires-Dist: coverage ; extra == 'tests'
Requires-Dist: pytest ; extra == 'tests'
Requires-Dist: pytest-cov ; extra == 'tests'
Requires-Dist: xdoctest ; extra == 'tests'
